sphinx_metadata_figure/__init__.py
sphinx_metadata_figure/_version.py
sphinx_metadata_figure/assets/metadata_figure.css
sphinx_metadata_figure/translations/README.md
sphinx_metadata_figure/translations/_convert.py
sphinx_metadata_figure/translations/untranslate.json
sphinx_metadata_figure/translations/jsons/AllRightsReserved.json
sphinx_metadata_figure/translations/jsons/Attribution.json
sphinx_metadata_figure/translations/jsons/Author.json
sphinx_metadata_figure/translations/jsons/Copyright.json
sphinx_metadata_figure/translations/jsons/Date.json
sphinx_metadata_figure/translations/jsons/License.json
sphinx_metadata_figure/translations/jsons/PexelsLicense.json
sphinx_metadata_figure/translations/jsons/PixabayLicense.json
sphinx_metadata_figure/translations/jsons/Proprietary.json
sphinx_metadata_figure/translations/jsons/PublicDomain.json
sphinx_metadata_figure/translations/jsons/Source.json
sphinx_metadata_figure/translations/jsons/UnsplashLicense.json
sphinx_metadata_figure/translations/jsons/VecteezyFreeLicense.json
sphinx_metadata_figure/translations/locales/ar/LC_MESSAGES/sphinx_metadata_figure.mo
sphinx_metadata_figure/translations/locales/ar/LC_MESSAGES/sphinx_metadata_figure.po
sphinx_metadata_figure/translations/locales/bn/LC_MESSAGES/sphinx_metadata_figure.mo
sphinx_metadata_figure/translations/locales/bn/LC_MESSAGES/sphinx_metadata_figure.po
sphinx_metadata_figure/translations/locales/cs/LC_MESSAGES/sphinx_metadata_figure.mo
sphinx_metadata_figure/translations/locales/cs/LC_MESSAGES/sphinx_metadata_figure.po
sphinx_metadata_figure/translations/locales/de/LC_MESSAGES/sphinx_metadata_figure.mo
sphinx_metadata_figure/translations/locales/de/LC_MESSAGES/sphinx_metadata_figure.po
sphinx_metadata_figure/translations/locales/el/LC_MESSAGES/sphinx_metadata_figure.mo
sphinx_metadata_figure/translations/locales/el/LC_MESSAGES/sphinx_metadata_figure.po
sphinx_metadata_figure/translations/locales/es/LC_MESSAGES/sphinx_metadata_figure.mo
sphinx_metadata_figure-1.4.0.dist-info/METADATA
sphinx_metadata_figure-1.4.0.dist-info/WHEEL
sphinx_metadata_figure-1.4.0.dist-info/licenses/LICENSE
sphinx_metadata_figure-1.4.0.dist-info/RECORD
