Metadata-Version: 2.4
Name: sphinx-metadata-figure
Version: 1.4.0
Summary: A Sphinx extension that provides an interface to add metadata to figures and display the metadata.
Author-email: Dennis den Ouden-van der Horst <d.denouden-vanderhorst@tudelft.nl>, Kwangjin Lee <kwangjinlee@tudelft.nl>
License: MIT License
License-File: LICENSE
Requires-Python: >=3.10
Requires-Dist: myst-nb
Requires-Dist: sphinx
